{
  "weight": 1,
  "description": {
    "translate": "enchantment.nope_runes.soul_shearing",
    "color": "yellow"
  },
  "slots": [
    "mainhand"
  ],
  "supported_items": "minecraft:shears",
  "max_level": 1,
  "anvil_cost": 12,
  "min_cost": {
    "base": 15,
    "per_level_above_first": 0
  },
  "max_cost": {
    "base": 65,
    "per_level_above_first": 0
  },
  "effects": {
    "minecraft:tick": [
      {
        "requirements": [
          {
            "condition": "minecraft:inverted",
            "term": {
              "condition": "minecraft:entity_properties",
              "entity": "this",
              "predicate": {
                "equipment": {
                  "mainhand": {
                    "items": "minecraft:shears",
                    "predicates": {
                      "minecraft:custom_data": {
                        "has_soul_shearing_enchant": 1
                      }
                    }
                  }
                }
              }
            }
          }
        ],
        "effect": {
          "type": "run_function",
          "function": "nope_runes:xp_siphon/soul_shearing_cons_setup"
        }
      }
    ]
  }
}