{
  "weight": 1,
  "description": {
    "translate": "enchantment.nope_runes.soul_shearing",
    "color": "yellow"
  },
  "slots": [
    "mainhand"
  ],
  "supported_items": "minecraft:shears",
  "max_level": 1,
  "anvil_cost": 12,
  "min_cost": {
    "base": 15,
    "per_level_above_first": 0
  },
  "max_cost": {
    "base": 65,
    "per_level_above_first": 0
  },
  "effects": {
    "minecraft:tick": [
      
      {
        "requirements": [
          {
            "condition": "all_of",
            "terms": [
              {
                "condition": "minecraft:inverted",
                "term": {
                  "condition": "minecraft:entity_properties",
                  "entity": "this",
                  "predicate": {
                    "equipment": {
                      "mainhand": {
                        "items": "minecraft:shears",
                        "components": {
                          "custom_data": {
                            "has_soul_shearing_enchant": 1
                          }
                        }
                      }
                    }
                  }
                }
              },
              {
                "condition": "minecraft:inverted",
                "term": {
                  "condition": "minecraft:entity_properties",
                  "entity": "this",
                  "predicate": {
                    "equipment": {
                      "mainhand": {
                        "items": "minecraft:shears",
                        "predicates": {
                          "custom_data": {
                            "soul_shears":1
                          }
                        }
                      }
                    }
                  }
                }
              }
            ]
          }
        ],
        "effect": {
          "type": "run_function",
          "function": "soul_alchemy:xp_siphon/soul_shearing_cons_setup_v"
        }
      },
      {
        "requirements": [
          {
            "condition": "all_of",
            "terms": [
              {
                "condition": "minecraft:inverted",
                "term": {
                  "condition": "minecraft:entity_properties",
                  "entity": "this",
                  "predicate": {
                    "equipment": {
                      "mainhand": {
                        "items": "minecraft:shears",
                        "components": {
                          "custom_data": {
                            "has_soul_shearing_enchant": 1
                          }
                        }
                      }
                    }
                  }
                }
              },
              {
                "condition": "minecraft:entity_properties",
                "entity": "this",
                "predicate": {
                  "equipment": {
                    "mainhand": {
                      "items": "minecraft:shears",
                      "components": {
                        "custom_data": {
                          "soul_shears":1
                        }
                      }
                    }
                  }
                }
              }
            ]
          }
        ],
        "effect": {
          "type": "run_function",
          "function": "soul_alchemy:xp_siphon/soul_shearing_cons_setup_s"
        }
      }
    ]
  }
}